fw_gear_rtstruct_to_nifti/__init__.py
fw_gear_rtstruct_to_nifti/creator.py
fw_gear_rtstruct_to_nifti/fixers.py
fw_gear_rtstruct_to_nifti/main.py
fw_gear_rtstruct_to_nifti/parser.py
fw_gear_rtstruct_to_nifti/prepper.py
fw_gear_rtstruct_to_nifti/rt_utils_with_buffer/__init__.py
fw_gear_rtstruct_to_nifti/rt_utils_with_buffer/image_helper.py
fw_gear_rtstruct_to_nifti/rt_utils_with_buffer/rtstruct.py
fw_gear_rtstruct_to_nifti/rt_utils_with_buffer/rtstruct_builder.py
fw_gear_rtstruct_to_nifti/utils.py
fw_gear_rtstruct_to_nifti-0.2.5.dist-info/LICENSE
fw_gear_rtstruct_to_nifti-0.2.5.dist-info/METADATA
fw_gear_rtstruct_to_nifti-0.2.5.dist-info/WHEEL
fw_gear_rtstruct_to_nifti-0.2.5.dist-info/RECORD
