Metadata-Version: 2.1
Name: fw-gear-rtstruct-to-nifti
Version: 0.2.5
Summary: Flywheel Gear for converting RTStruct ROIs to NIfTI
Home-page: https://gitlab.com/flywheel-io/scientific-solutions/gears/rtstruct-to-nifti
License: MIT
Keywords: Flywheel,Gears
Author: Flywheel
Author-email: support@flywheel.io
Requires-Python: >=3.12,<4.0
Classifier: License :: OSI Approved :: MIT License
Classifier: Programming Language :: Python :: 3
Classifier: Programming Language :: Python :: 3.12
Classifier: Topic :: Scientific/Engineering
Requires-Dist: flywheel-gear-toolkit (>=0.6,<0.7)
Requires-Dist: flywheel-sdk (>=16.8.0,<17.0.0)
Requires-Dist: fw-file (>=3.3.0,<4.0.0)
Requires-Dist: pandas (>=2.1.3,<3.0.0)
Requires-Dist: python-gdcm (>=3.0.24.1,<4.0.0.0)
Requires-Dist: rt-utils (>=1.2.7,<2.0.0)
Requires-Dist: shapely (>=2.0.3,<3.0.0)
Requires-Dist: simpleitk (>=2.4.0,<3.0.0)
Project-URL: Repository, https://gitlab.com/flywheel-io/scientific-solutions/gears/rtstruct-to-nifti
